indexed_heapq/__init__.py
indexed_heapq/indexed_heapq.py
indexed_heapq/py.typed
indexed_heapq-0.1.0.dist-info/LICENSE
indexed_heapq-0.1.0.dist-info/METADATA
indexed_heapq-0.1.0.dist-info/WHEEL
indexed_heapq-0.1.0.dist-info/top_level.txt
indexed_heapq-0.1.0.dist-info/RECORD
