Metadata-Version: 2.2
Name: indexed-heapq
Version: 0.1.0
Summary: Indexed Heap Queue (Priority Queue)
Author: Simeon Filipov
License: MIT License
Project-URL: Source, https://github.com/sfilipov/indexed-heapq
Project-URL: Tracker, https://github.com/sfilipov/indexed-heapq/issues
Classifier: License :: OSI Approved :: MIT License
Classifier: Natural Language :: English
Classifier: Programming Language :: Python
Classifier: Programming Language :: Python :: 3
Classifier: Programming Language :: Python :: 3.9
Classifier: Programming Language :: Python :: 3.10
Classifier: Programming Language :: Python :: 3.11
Classifier: Programming Language :: Python :: 3.12
Classifier: Programming Language :: Python :: 3.13
Classifier: Programming Language :: Python :: Implementation :: CPython
Classifier: Typing :: Typed
Requires-Python: >=3.9
License-File: LICENSE
